{
    "type": [
        "Category:OSW268cc84d3dff4a7ba5fd489d53254cb0"
    ],
    "exact_ontology_match": [
        "http://qudt.org/vocab/unit/MilliMOL-PER-M3-DAY"
    ],
    "uuid": "0f0d0412-f8e3-5ed7-baec-5fbb3b1f9821",
    "name": "MillimolesPerCubicMetreDay",
    "label": [
        {
            "text": "MilliMoles per Cubic Metre Day",
            "lang": "en"
        }
    ],
    "description": [
        {
            "text": "Unavailable.",
            "lang": "en"
        }
    ],
    "main_symbol": "mmol/(m³·d)",
    "conversion_factor_from_si": 1.1574074074074074e-08,
    "ucum_codes": [
        "mmol.m-3.d-1"
    ],
    "factor_unit_scalar": 1,
    "factor_units": [
        {
            "exponent": -3
        },
        {
            "exponent": 1
        },
        {
            "exponent": -1
        }
    ]
}