{
    "type": [
        "Category:OSW6c2aea028a8647cd97f5d7c65c09cd44"
    ],
    "exact_ontology_match": [
        "http://qudt.org/vocab/unit/BQ-PER-KiloGM"
    ],
    "uuid": "03b25e9a-7cef-5ade-b7f3-d5f82115dfc3",
    "name": "BecquerelPerKilogram",
    "label": [
        {
            "text": "Becquerel per KiloGram",
            "lang": "en"
        }
    ],
    "description": [
        {
            "text": "\"Becquerel per Kilogram\" is used to describe radioactivity, which is often expressed in becquerels per unit of volume or weight, to express how much radioactive material is contained in a sample.",
            "lang": "en"
        }
    ],
    "main_symbol": "Bq/kg",
    "conversion_factor_from_si": 1.0,
    "ucum_codes": [
        "Bq.kg-1",
        "Bq/kg"
    ],
    "factor_units": [
        {
            "uuid": "b54647dd-0671-5540-89d6-3ed7aaddace5",
            "unit": "Item:OSW3c9bf4c3682f5a52b6e99f7ad7949903#OSWda255533fa615a42b08ddb7aaa8236f0",
            "exponent": -1
        },
        {
            "uuid": "95e505ca-d542-5bf6-b93a-f34f6ee5f94b",
            "unit": "Item:OSW06027f437dd357449795ec4d0e001467",
            "exponent": 1
        }
    ]
}