{
    "type": [
        "Category:OSW268cc84d3dff4a7ba5fd489d53254cb0"
    ],
    "exact_ontology_match": [
        "http://qudt.org/vocab/unit/GM-K"
    ],
    "uuid": "7b82dfcb-fc22-546f-a1bd-69b1f1d373da",
    "name": "GramKelvin",
    "label": [
        {
            "text": "Gram Kelvin",
            "lang": "en"
        }
    ],
    "description": [
        {
            "text": "$\\textit{Gram Kelvin}$ is a unit for 'Mass Temperature' expressed as $g-K$. It represents the product of gram and kelvin.",
            "lang": "en"
        }
    ],
    "main_symbol": "g·K",
    "conversion_factor_from_si": 0.001,
    "ucum_codes": [
        "g.K"
    ],
    "factor_unit_scalar": 1,
    "factor_units": [
        {
            "exponent": 1
        },
        {
            "exponent": 1
        }
    ],
    "composed_units": [
        {
            "type": [
                "Category:OSWd2520fa016844e01af0097a85bb25b25"
            ],
            "uuid": "fd24f942-5d81-5d66-beab-746eecaf5926",
            "osw_id": "Item:OSW7b82dfcbfc22546fa1bd69b1f1d373da#OSWfd24f9425d815d66beab746eecaf5926",
            "conversion_factor_to_main_unit": 1000.0,
            "conversion_factor_from_si": 1.0,
            "main_symbol": "kg·K",
            "ucum_codes": [
                "kg.K"
            ],
            "factor_units": [
                {
                    "exponent": 1
                },
                {
                    "exponent": 1
                }
            ]
        }
    ]
}