{
    "type": [
        "Category:OSW6c2aea028a8647cd97f5d7c65c09cd44"
    ],
    "exact_ontology_match": [
        "http://qudt.org/vocab/unit/PA2-PER-SEC2"
    ],
    "uuid": "928a2bd0-b7c0-5745-b866-c35c4a12772d",
    "name": "SquarePascalPerSquareSecond",
    "label": [
        {
            "text": "Square Pascal per Square Second",
            "lang": "en"
        }
    ],
    "main_symbol": "Pa²/s²",
    "conversion_factor_from_si": 1.0,
    "ucum_codes": [
        "Pa2.s-2"
    ],
    "factor_units": [
        {
            "uuid": "47d0ad13-4e4d-5bed-8bca-752e1c968a02",
            "unit": "Item:OSWb663e6bff3595e7b93b28fffce66c50c",
            "exponent": 2
        },
        {
            "uuid": "5138b5fe-c0aa-58f2-a4b6-7ab6693fce7d",
            "unit": "Item:OSW85302b21cf045998b80f38c9fdb88f84",
            "exponent": -2
        }
    ]
}