{
    "type": [
        "Category:OSW6c2aea028a8647cd97f5d7c65c09cd44"
    ],
    "exact_ontology_match": [
        "http://qudt.org/vocab/unit/M-GM"
    ],
    "uuid": "b75542bd-3aa1-53d2-95c5-a791cf31a2ed",
    "name": "MetreGram",
    "label": [
        {
            "text": "Metre Gram",
            "lang": "en"
        }
    ],
    "description": [
        {
            "text": "product of SI units metre and gram given as dimensional product dim Q = L**$a} M**$b} T**$g} I**$d} $TH**$e} N**$z} J**$i}",
            "lang": "en"
        }
    ],
    "main_symbol": "m·g",
    "conversion_factor_from_si": 1000.0,
    "ucum_codes": [
        "m.g"
    ],
    "factor_units": [
        {
            "uuid": "7f3e9dae-65a8-5c14-908f-6ac95c3f8f2b",
            "unit": "Item:OSWf101d25e944856e3bd4b4c9863db7de2",
            "exponent": 1
        },
        {
            "uuid": "55a099c9-0e0f-5034-86b9-4a2089199431",
            "unit": "Item:OSW3c9bf4c3682f5a52b6e99f7ad7949903",
            "exponent": 1
        }
    ],
    "composed_units": [
        {
            "type": [
                "Category:OSW6ef70c808fb54abbbacb059c285713d4"
            ],
            "uuid": "4a5d124e-14e4-5b8c-95be-bb544ce245b6",
            "osw_id": "Item:OSWb75542bd3aa153d295c5a791cf31a2ed#OSW4a5d124e14e45b8c95bebb544ce245b6",
            "conversion_factor_from_si": 1.0,
            "main_symbol": "m·kg",
            "ucum_codes": [
                "m.kg"
            ],
            "factor_units": [
                {
                    "uuid": "e75e0081-1089-5911-9dfc-979da75f3904",
                    "unit": "Item:OSW3c9bf4c3682f5a52b6e99f7ad7949903#OSWda255533fa615a42b08ddb7aaa8236f0",
                    "exponent": 1
                },
                {
                    "uuid": "2667f1d4-8268-5851-81b5-45520525b49d",
                    "unit": "Item:OSWf101d25e944856e3bd4b4c9863db7de2",
                    "exponent": 1
                }
            ]
        }
    ]
}