{
    "type": [
        "Category:OSW6c2aea028a8647cd97f5d7c65c09cd44"
    ],
    "exact_ontology_match": [
        "http://qudt.org/vocab/unit/N-M-PER-DEG"
    ],
    "uuid": "c52e27ac-442e-51e3-9ea2-c81a8b18a1bc",
    "name": "NewtonMetrePerDegree",
    "label": [
        {
            "text": "Newton Metre per Degree",
            "lang": "en"
        }
    ],
    "description": [
        {
            "text": "product of the SI derived unit newton and the SI base unit metre divided by the unit degree",
            "lang": "en"
        }
    ],
    "main_symbol": "N·m/°",
    "conversion_factor_from_si": 57.2957795785523,
    "ucum_codes": [
        "N.m.deg-1",
        "N.m/deg"
    ],
    "factor_units": [
        {
            "uuid": "ff934c1a-b44d-55f5-a683-6a3a9e14f0d6",
            "unit": "Item:OSWf101d25e944856e3bd4b4c9863db7de2",
            "exponent": 1
        },
        {
            "uuid": "cd1cfef9-03e4-5d11-8146-f25a2a7ef8f6",
            "unit": "Item:OSW8113ac9c25615c21902a9447ab03cc0a",
            "exponent": 1
        },
        {
            "uuid": "25c6dc58-c90d-53d5-b647-0cfc79e84408",
            "unit": "Item:OSW308ac27be52b5fbe85d647c7429f32f1",
            "exponent": -1
        }
    ],
    "composed_units": [
        {
            "type": [
                "Category:OSW6ef70c808fb54abbbacb059c285713d4"
            ],
            "uuid": "594d046f-9dd7-5e6b-abaf-afcc00da5467",
            "osw_id": "Item:OSWc52e27ac442e51e39ea2c81a8b18a1bc#OSW594d046f9dd75e6babafafcc00da5467",
            "conversion_factor_from_si": 57295.7795785523,
            "main_symbol": "kN·m/°",
            "ucum_codes": [
                "kN.m.deg-1"
            ],
            "factor_units": [
                {
                    "uuid": "2797e9f6-e396-55b5-81d6-84cfe3f60e63",
                    "unit": "Item:OSW8113ac9c25615c21902a9447ab03cc0a#OSW9e26f43774ed54c9b9bf757fca6ad5e7",
                    "exponent": 1
                },
                {
                    "uuid": "304d1627-4c5d-5b25-bad9-c52b44fcd988",
                    "unit": "Item:OSW308ac27be52b5fbe85d647c7429f32f1",
                    "exponent": -1
                },
                {
                    "uuid": "6413b983-55fd-5636-9e21-757aaa48e781",
                    "unit": "Item:OSWf101d25e944856e3bd4b4c9863db7de2",
                    "exponent": 1
                }
            ]
        }
    ]
}