{
    "type": [
        "Category:OSW268cc84d3dff4a7ba5fd489d53254cb0"
    ],
    "exact_ontology_match": [
        "http://qudt.org/vocab/unit/MilliL-PER-DAY"
    ],
    "uuid": "da34b5bb-0a15-516f-ba29-781df0096e7f",
    "name": "MillilitrePerDay",
    "label": [
        {
            "text": "MilliLitre per Day",
            "lang": "en"
        }
    ],
    "description": [
        {
            "text": "0.001-fold of the unit litre divided by the unit day",
            "lang": "en"
        }
    ],
    "main_symbol": "mL/d",
    "conversion_factor_from_si": 1.1574074074074074e-11,
    "ucum_codes": [
        "mL.d-1",
        "mL/d"
    ],
    "factor_unit_scalar": 1,
    "factor_units": [
        {
            "exponent": 1
        },
        {
            "exponent": -1
        }
    ]
}