{
    "type": [
        "Category:OSW6c2aea028a8647cd97f5d7c65c09cd44"
    ],
    "exact_ontology_match": [
        "http://qudt.org/vocab/unit/TONNE-PER-DAY"
    ],
    "uuid": "dca2b4ec-25b6-5997-86cd-88de8e1b220f",
    "name": "TonnePerDay",
    "label": [
        {
            "text": "Tonne per Day",
            "lang": "en"
        }
    ],
    "description": [
        {
            "text": "metric unit tonne divided by the unit for time day",
            "lang": "en"
        }
    ],
    "main_symbol": "t/d",
    "conversion_factor_from_si": 0.011574074074074073,
    "ucum_codes": [
        "t.d-1",
        "t/d"
    ],
    "factor_units": [
        {
            "uuid": "0798ee3f-564e-5e4a-bb36-c7e96e8ac257",
            "unit": "Item:OSW12c412031b9556848d70154dca0e1d13",
            "exponent": 1
        },
        {
            "uuid": "73090754-9037-5a14-8723-6141f306b6f1",
            "unit": "Item:OSWc90e307854c453be958300304ca8185e",
            "exponent": -1
        }
    ]
}